subarray
