Metadata-Version: 2.1
Name: subarray
Version: 0.2
Summary: get 2D sub array slices from a large 2D array
Home-page: https://github.com/tasin-megamind/subarray
Author: Tasin Nawaz
Author-email: tasin.buet@gmail.com
License: TN
Platform: UNKNOWN
